ibmcloud_iam/__init__.py
ibmcloud_iam/pdp.py
ibmcloud_iam/py.typed
ibmcloud_iam/token.py
ibmcloud_iam-0.1.7.dist-info/LICENSE
ibmcloud_iam-0.1.7.dist-info/METADATA
ibmcloud_iam-0.1.7.dist-info/WHEEL
ibmcloud_iam-0.1.7.dist-info/top_level.txt
ibmcloud_iam-0.1.7.dist-info/RECORD
