Metadata-Version: 2.1
Name: ibmcloud-iam
Version: 0.1.7
Summary: A collection of Python modules used for interacting with IBMCloud IAM API services
Home-page: https://github.com/mrodden/ibmcloud-iam-python-client
Author: Mathew Odden
Author-email: mrodden@us.ibm.com
License: UNKNOWN
Platform: UNKNOWN
Classifier: Programming Language :: Python :: 3
Classifier: Programming Language :: Python :: 3.5
Classifier: Programming Language :: Python :: 3.6
Classifier: Programming Language :: Python :: 3.7
Classifier: License :: OSI Approved :: Apache Software License
Requires-Python: >=3.6
License-File: LICENSE
Requires-Dist: requests[security]
Requires-Dist: pyjwt (<2.5,>=2.1.0)
Requires-Dist: redstone
Provides-Extra: docs
Requires-Dist: sphinx (>=3.1) ; extra == 'docs'
Requires-Dist: sphinx-rtd-theme ; extra == 'docs'
